{
  "games": {
    "default - 30-9-2018": {
      "traffic": [
        {
          "tgtAltitude": 14000,
          "tgtDirection": 240,
          "tgtSpeed": 320,
          "operatorId": 19,
          "speed": 320,
          "altitude": 14000,
          "heading": 240,
          "x": 1110.605,
          "y": 622.2,
          "flight": 1653,
          "path": [
            [
              1114.347,
              624.36
            ],
            [
              1122.661,
              629.16
            ],
            [
              1130.974,
              633.96
            ],
            [
              1139.288,
              638.76
            ],
            [
              1147.602,
              643.56
            ],
            [
              1159.782,
              650.592
            ],
            [
              1168.013,
              655.344
            ],
            [
              1176.243,
              660.096
            ],
            [
              1184.474,
              664.848
            ]
          ],
          "typeId": 11,
          "routeType": 0,
          "textRotation": 0
        },
        {
          "tgtAltitude": 12000,
          "tgtDirection": 266,
          "tgtSpeed": 330,
          "operatorId": 7,
          "speed": 330,
          "altitude": 12000,
          "heading": 266,
          "x": 1078.779,
          "y": 385.929,
          "flight": 230,
          "path": [
            [
              1083.223,
              386.24
            ],
            [
              1093.099,
              386.931
            ],
            [
              1102.975,
              387.621
            ],
            [
              1112.851,
              388.312
            ],
            [
              1122.727,
              389.002
            ],
            [
              1137.195,
              390.014
            ],
            [
              1146.972,
              390.698
            ],
            [
              1156.749,
              391.381
            ],
            [
              1166.526,
              392.065
            ]
          ],
          "typeId": 3,
          "routeType": 0,
          "textRotation": 0
        },
        {
          "tgtAltitude": 13000,
          "tgtDirection": 90,
          "tgtSpeed": 300,
          "operatorId": 1,
          "speed": 300,
          "altitude": 13000,
          "heading": 90,
          "x": 183.375,
          "y": 360,
          "flight": 60,
          "path": [
            [
              179.325,
              360
            ],
            [
              170.325,
              360
            ],
            [
              161.325,
              360
            ],
            [
              152.325,
              360
            ],
            [
              143.325,
              360
            ],
            [
              130.14,
              360
            ],
            [
              121.23,
              360
            ],
            [
              112.32,
              360
            ],
            [
              103.41,
              360
            ]
          ],
          "typeId": 12,
          "routeType": 0,
          "textRotation": 0
        },
        {
          "tgtAltitude": 15000,
          "tgtDirection": 5,
          "tgtSpeed": 320,
          "operatorId": 8,
          "speed": 0,
          "altitude": 0,
          "heading": 5,
          "x": 643.479,
          "y": 342.613,
          "flight": 122,
          "path": [],
          "typeId": 6,
          "routeType": 1,
          "textRotation": 0,
          "rwy": "36",
          "outboundWaypoint": "EZOS",
          "waiting": true
        },
        {
          "tgtAltitude": 15000,
          "tgtDirection": 5,
          "tgtSpeed": 320,
          "operatorId": 10,
          "speed": 0,
          "altitude": 0,
          "heading": 5,
          "x": 643.479,
          "y": 342.613,
          "flight": 1746,
          "path": [],
          "typeId": 8,
          "routeType": 1,
          "textRotation": 0,
          "rwy": "36",
          "outboundWaypoint": "EZOS",
          "waiting": true
        },
        {
          "tgtAltitude": 16000,
          "tgtDirection": 340,
          "tgtSpeed": 320,
          "operatorId": 14,
          "speed": 320,
          "altitude": 16000,
          "heading": 340,
          "x": 183.101,
          "y": 183.804,
          "flight": 1186,
          "path": [
            [
              184.578,
              179.744
            ],
            [
              187.862,
              170.723
            ],
            [
              191.145,
              161.702
            ],
            [
              194.429,
              152.681
            ],
            [
              197.712,
              143.66
            ],
            [
              202.522,
              130.444
            ],
            [
              205.773,
              121.514
            ],
            [
              209.023,
              112.583
            ],
            [
              212.274,
              103.652
            ]
          ],
          "typeId": 10,
          "routeType": 2,
          "textRotation": 0,
          "outboundWaypoint": "EDOS"
        },
        {
          "tgtAltitude": 3000,
          "tgtDirection": "NORTH",
          "tgtSpeed": 120,
          "operatorId": null,
          "speed": 120,
          "altitude": 2552.4,
          "heading": 5,
          "x": 649.109,
          "y": 406.962,
          "flight": null,
          "path": [
            [
              648.967,
              405.348
            ],
            [
              648.654,
              401.761
            ],
            [
              648.34,
              398.175
            ],
            [
              648.026,
              394.589
            ],
            [
              647.712,
              391.003
            ],
            [
              647.253,
              385.749
            ],
            [
              646.942,
              382.198
            ],
            [
              646.631,
              378.648
            ],
            [
              646.321,
              375.097
            ]
          ],
          "typeId": 18,
          "routeType": 5,
          "textRotation": 0,
          "rwy": "36",
          "tgtVfrState": 6,
          "outboundWaypoint": "NORTH",
          "regNum": "KAF76",
          "waiting": false
        },
        {
          "tgtAltitude": 2000,
          "tgtDirection": 266,
          "tgtSpeed": 120,
          "operatorId": null,
          "speed": 120,
          "altitude": 2000,
          "heading": 266,
          "x": 1206.829,
          "y": 394.883,
          "flight": null,
          "path": [
            [
              1208.445,
              394.996
            ],
            [
              1212.036,
              395.247
            ],
            [
              1215.627,
              395.499
            ],
            [
              1219.218,
              395.75
            ],
            [
              1222.81,
              396.001
            ],
            [
              1228.071,
              396.369
            ],
            [
              1231.626,
              396.617
            ],
            [
              1235.181,
              396.866
            ],
            [
              1238.737,
              397.115
            ]
          ],
          "typeId": 18,
          "routeType": 6,
          "textRotation": 0,
          "regNum": "FVS29",
          "tgtVfrState": 0
        },
        {
          "tgtAltitude": 4000,
          "tgtDirection": 47,
          "tgtSpeed": 120,
          "operatorId": null,
          "speed": 120,
          "altitude": 4000,
          "heading": 47,
          "x": 303.645,
          "y": 50.025,
          "flight": null,
          "path": [
            [
              302.46,
              48.92
            ],
            [
              299.827,
              46.465
            ],
            [
              297.194,
              44.009
            ],
            [
              294.561,
              41.554
            ],
            [
              291.929,
              39.099
            ],
            [
              288.071,
              35.502
            ],
            [
              285.465,
              33.071
            ],
            [
              282.858,
              30.641
            ],
            [
              280.252,
              28.21
            ]
          ],
          "typeId": 18,
          "routeType": 7,
          "textRotation": 0,
          "regNum": "GPH68",
          "tgtVfrState": 0,
          "tgs": 1
        },
        {
          "tgtAltitude": 1025,
          "tgtDirection": "36",
          "tgtSpeed": 120,
          "operatorId": null,
          "speed": 120,
          "altitude": 1025,
          "heading": 185,
          "x": 627.459,
          "y": 342.853,
          "flight": null,
          "path": [
            [
              627.6,
              344.467
            ],
            [
              627.914,
              348.053
            ],
            [
              628.228,
              351.639
            ],
            [
              628.542,
              355.226
            ],
            [
              628.855,
              358.812
            ],
            [
              629.315,
              364.066
            ],
            [
              630.395,
              367.379
            ],
            [
              633.568,
              368.735
            ],
            [
              637.118,
              368.424
            ]
          ],
          "typeId": 18,
          "routeType": 4,
          "textRotation": 0,
          "rwy": "36",
          "regNum": "DVU15",
          "tgtVfrState": 0,
          "waiting": false,
          "tgs": 1,
          "dirty": true,
          "tgtHeading": 5
        },
        {
          "tgtAltitude": 11000,
          "tgtDirection": 105,
          "tgtSpeed": 300,
          "operatorId": 1,
          "speed": 300,
          "altitude": 11000,
          "heading": 105,
          "x": 32.6,
          "y": 351.265,
          "flight": 835,
          "path": [
            [
              28.688,
              352.313
            ],
            [
              19.995,
              354.642
            ],
            [
              11.301,
              356.972
            ],
            [
              2.608,
              359.301
            ]
          ],
          "typeId": 14,
          "routeType": 2,
          "textRotation": 0,
          "outboundWaypoint": "EZOS"
        }
      ],
      "started": true,
      "log": [
        "QTR1653: EHZM approach, QTR1653 at 140 with Oscar.",
        "ATC: QTR1653, EHZM approach, maintain current heading.",
        "COA230: EHZM approach, COA230 at 120 with Oscar.",
        "ATC: COA230, EHZM approach, maintain current heading.",
        "DLT60: EHZM approach, DLT60 at 130.",
        "ATC: DLT60, information Oscar is current, altimeter 30.71, maintain current heading.",
        "DLH122: EHZM approach, with you for 36.",
        "ATC: DLH122, EHZM approach, hold short 36.",
        "DLH122: Roger hold short of 36, DLH122.",
        "CSN1746: EHZM approach, with you for 36.",
        "ATC: CSN1746, EHZM approach, hold short 36.",
        "CSN1746: Roger hold short of 36, CSN1746.",
        "KAF76: EHZM approach, with you for 36.",
        "ATC: KAF76, EHZM approach, hold short 36.",
        "KAF76: Roger hold short of 36, KAF76.",
        "ATC: KAF76, takeoff runway 36, the wind is 41 at 11 knots",
        "KAF76: takeoff runway 36, the wind is 41 at 11 knots, KiloAlfaFoxtrot76",
        "ATC: DVU15, takeoff runway 36, the wind is 41 at 11 knots",
        "DVU15: takeoff runway 36, the wind is 41 at 11 knots, DeltaVictorUniform15"
      ],
      "selfLog": [
        "ATC: QTR1653, EHZM approach, maintain current heading.",
        "ATC: COA230, EHZM approach, maintain current heading.",
        "ATC: DLT60, information Oscar is current, altimeter 30.71, maintain current heading.",
        "ATC: DLH122, EHZM approach, hold short 36.",
        "ATC: CSN1746, EHZM approach, hold short 36.",
        "ATC: KAF76, EHZM approach, hold short 36.",
        "ATC: KAF76, takeoff runway 36, the wind is 41 at 11 knots",
        "ATC: DVU15, takeoff runway 36, the wind is 41 at 11 knots"
      ],
      "pathCounter": 9,
      "mapName": "default",
      "id": "default",
      "arrivals": 0,
      "departures": 0,
      "enroutes": 0,
      "distanceVialations": 0,
      "winddir": 41,
      "windspd": 11,
      "unpermittedDepartures": 0
    }
  },
  "settings": {
    "ga": true,
    "enroute": true
  }
}